{
  "policy_info": {
    "state": "Maryland",
    "policy_type": "minimum age",
    "implementation_year": 1997
  },
  "impact_summary": {
    "before_rate": 8.44,
    "after_rate": 6.23,
    "change_percent": -26.2,
    "statistically_significant": "True",
    "p_value": 0.000145
  },
  "time_series_data": {
    "before_period": [
      {
        "year": 1995,
        "incident_rate": 8.575000189356413
      },
      {
        "year": 1996,
        "incident_rate": 8.308281419714646
      }
    ],
    "after_period": [
      {
        "year": 1998,
        "incident_rate": 6.44861111826773
      },
      {
        "year": 1999,
        "incident_rate": 5.997147097913184
      },
      {
        "year": 2000,
        "incident_rate": 5.891861593040709
      },
      {
        "year": 2001,
        "incident_rate": 6.329760102719482
      },
      {
        "year": 2002,
        "incident_rate": 6.482809525830538
      }
    ]
  },
  "control_comparison": [
    {
      "state": "Georgia",
      "before_rate": 5.075895284950478,
      "after_rate": 3.9738975907741456,
      "change_percent": -21.710410327881384
    },
    {
      "state": "Arizona",
      "before_rate": 5.251802356802118,
      "after_rate": 4.6996046088077055,
      "change_percent": -10.514442670890077
    },
    {
      "state": "Texas",
      "before_rate": 4.354080650537,
      "after_rate": 3.232349848696587,
      "change_percent": -25.7627474516823
    }
  ],
  "diff_in_diff": -6.87
}